{
  "ComponentIndexes": {
    "sideNavigation": 7,
    "sideNavigation_def": 3,
    "sideNavigation_Ld": 3,
    "sideNavigation_pb": 3,
    "sideNavigation_pb_1": 3,
    "sideNavigation_plan": 3,
    "sideNavigation_prod": 3,
    "sideNavigation_wo": 3
  },
  "ControlUniqueGuids": {},
  "ControlUniqueIds": {
    "2_lbMiniDash_sn": 10,
    "addImgIcon": 224,
    "AddPicture1": 54,
    "App": 1,
    "att_check_2": 244,
    "att_check_3": 469,
    "Att_check_DataCard1_2": 241,
    "Att_check_DataCard1_3": 466,
    "btnAdd_att": 273,
    "btnAdd_wo": 537,
    "btnCommit_def": 252,
    "btnCommit_def_1": 477,
    "btnCommitwithoutPatch": 251,
    "btnCommitwithoutPatch_1": 476,
    "btnDef": 13,
    "btnGrid": 126,
    "btnGroup_att": 478,
    "btnGroup_def": 253,
    "btnGroup_prod": 479,
    "btnJob": 12,
    "btnPlan": 15,
    "btnPO": 14,
    "btnSave": 125,
    "btnSave_att": 274,
    "btnSave_prod": 388,
    "btnSearch": 124,
    "btnSearch_prod": 387,
    "btnST": 16,
    "btnWP": 17,
    "btnWP_1": 20,
    "btnWP_2": 19,
    "btnWP_3": 22,
    "btnWP_4": 23,
    "Button1": 49,
    "Button2": 534,
    "Button3": 535,
    "ButtonTimer_prod": 454,
    "cb_isClosed": 282,
    "cbbWorker": 216,
    "cbClosing": 536,
    "cbInclWO": 137,
    "Comment_DataCard1_2": 246,
    "Comment_DataCard1_3": 471,
    "commitForm_def": 230,
    "commitForm_def_1": 455,
    "contCommit_def": 227,
    "contCommit_def_1": 451,
    "contConfirm": 39,
    "contDataTable_wo": 487,
    "contEditForm": 37,
    "contFilter_def": 32,
    "contFilter_prod": 268,
    "contForm": 179,
    "contForm_att": 327,
    "contForm_prod": 414,
    "contHeader_att": 303,
    "contHeader_def": 158,
    "contHeader_mh": 381,
    "contHeader_prod": 397,
    "contHeader_wo": 283,
    "contHeader3": 138,
    "contNaviList": 8,
    "contOutput_mh": 391,
    "contWorkOrder": 130,
    "contWorkOrder_prod": 277,
    "Customer_DataCard1": 68,
    "Customer_DataCard2": 499,
    "Customer_열1": 542,
    "Customer_열2": 557,
    "DataCardKey10": 101,
    "DataCardKey11": 106,
    "DataCardKey12": 111,
    "DataCardKey13": 116,
    "DataCardKey14": 121,
    "DataCardKey15": 56,
    "DataCardKey16": 492,
    "DataCardKey16_2": 233,
    "DataCardKey16_3": 458,
    "DataCardKey17": 497,
    "DataCardKey17_2": 238,
    "DataCardKey17_3": 463,
    "DataCardKey18": 502,
    "DataCardKey18_2": 243,
    "DataCardKey18_3": 468,
    "DataCardKey19": 507,
    "DataCardKey19_2": 249,
    "DataCardKey19_3": 474,
    "DataCardKey2": 61,
    "DataCardKey20": 512,
    "DataCardKey21": 517,
    "DataCardKey22": 522,
    "DataCardKey23": 527,
    "DataCardKey24": 532,
    "DataCardKey3": 66,
    "DataCardKey4": 71,
    "DataCardKey5": 76,
    "DataCardKey6": 81,
    "DataCardKey7": 86,
    "DataCardKey8": 91,
    "DataCardKey9": 96,
    "DataCardValue10": 99,
    "DataCardValue11": 104,
    "DataCardValue12": 109,
    "DataCardValue13": 114,
    "DataCardValue14": 119,
    "DataCardValue15": 490,
    "DataCardValue16": 495,
    "DataCardValue17": 500,
    "DataCardValue18": 505,
    "DataCardValue18_2": 247,
    "DataCardValue18_3": 472,
    "DataCardValue19": 510,
    "DataCardValue2": 59,
    "DataCardValue20": 515,
    "DataCardValue21": 520,
    "DataCardValue22": 525,
    "DataCardValue23": 530,
    "DataCardValue3": 64,
    "DataCardValue4": 69,
    "DataCardValue5": 74,
    "DataCardValue6": 79,
    "DataCardValue7": 84,
    "DataCardValue8": 89,
    "DataCardValue9": 94,
    "DataTable+wo": 539,
    "DataTable2": 554,
    "DataTable3": 256,
    "Date_DataCard1": 93,
    "Date_열1": 563,
    "def_check_2": 239,
    "def_check_3": 464,
    "Def_check_DataCard1_2": 236,
    "Def_check_DataCard1_3": 461,
    "Description_열1": 561,
    "Description_열2": 260,
    "divider_prod": 379,
    "Divider_sn": 27,
    "divider1": 183,
    "divider1_1": 185,
    "divider1_10": 203,
    "divider1_11": 208,
    "divider1_12": 210,
    "divider1_13": 212,
    "divider1_15": 215,
    "divider1_16": 217,
    "divider1_17": 204,
    "divider1_18": 221,
    "divider1_19": 225,
    "divider1_2": 187,
    "divider1_20": 206,
    "divider1_21": 418,
    "divider1_22": 420,
    "divider1_23": 422,
    "divider1_24": 424,
    "divider1_25": 426,
    "divider1_26": 428,
    "divider1_27": 430,
    "divider1_28": 432,
    "divider1_29": 434,
    "divider1_3": 189,
    "divider1_30": 436,
    "divider1_31": 438,
    "divider1_32": 440,
    "divider1_33": 442,
    "divider1_34": 444,
    "divider1_35": 446,
    "divider1_36": 448,
    "divider1_37": 331,
    "divider1_38": 346,
    "divider1_39": 333,
    "divider1_4": 191,
    "divider1_40": 450,
    "divider1_41": 335,
    "divider1_42": 337,
    "divider1_43": 449,
    "divider1_44": 340,
    "divider1_45": 338,
    "divider1_46": 342,
    "divider1_47": 344,
    "divider1_48": 348,
    "divider1_49": 350,
    "divider1_5": 193,
    "divider1_50": 352,
    "divider1_51": 354,
    "divider1_52": 356,
    "divider1_53": 376,
    "divider1_54": 378,
    "divider1_55": 358,
    "divider1_56": 360,
    "divider1_57": 362,
    "divider1_58": 364,
    "divider1_59": 366,
    "divider1_6": 195,
    "divider1_60": 368,
    "divider1_61": 370,
    "divider1_62": 372,
    "divider1_63": 374,
    "divider1_64": 377,
    "divider1_65": 220,
    "divider1_7": 197,
    "divider1_8": 199,
    "divider1_9": 201,
    "drpDiv1": 211,
    "drpLineSel": 136,
    "drpLineSel_prod": 270,
    "drpLostDiv_prod": 443,
    "drpProcess_prod": 435,
    "drpShift_prod": 433,
    "EditForm": 51,
    "embededPowerBI": 483,
    "EndDate_열1": 263,
    "ErrorMessage10": 102,
    "ErrorMessage11": 107,
    "ErrorMessage12": 112,
    "ErrorMessage13": 117,
    "ErrorMessage14": 122,
    "ErrorMessage15": 57,
    "ErrorMessage16": 493,
    "ErrorMessage16_2": 235,
    "ErrorMessage16_3": 460,
    "ErrorMessage17": 498,
    "ErrorMessage17_2": 240,
    "ErrorMessage17_3": 465,
    "ErrorMessage18": 503,
    "ErrorMessage18_2": 245,
    "ErrorMessage18_3": 470,
    "ErrorMessage19": 508,
    "ErrorMessage19_2": 250,
    "ErrorMessage19_3": 475,
    "ErrorMessage2": 62,
    "ErrorMessage20": 513,
    "ErrorMessage21": 518,
    "ErrorMessage22": 523,
    "ErrorMessage23": 528,
    "ErrorMessage24": 533,
    "ErrorMessage3": 67,
    "ErrorMessage4": 72,
    "ErrorMessage5": 77,
    "ErrorMessage6": 82,
    "ErrorMessage7": 87,
    "ErrorMessage8": 92,
    "ErrorMessage9": 97,
    "Form1": 488,
    "galleryTemplate1": 181,
    "galleryTemplate1_1": 416,
    "galleryTemplate1_2": 329,
    "galleryTemplate2": 148,
    "galleryTemplate2_1": 292,
    "galProdHistory": 146,
    "galWorkOrder": 291,
    "gifGreetingFox": 571,
    "gifLeftArrow": 569,
    "Greeting_Ld": 570,
    "gridForm_att": 328,
    "gridForm_def": 180,
    "gridForm_prod": 415,
    "grpAddImg": 226,
    "grpSave": 123,
    "hdAbsent_att": 315,
    "hdActionTaken": 177,
    "hdAssembly_att": 319,
    "hdCleaning_att": 321,
    "hdDate": 160,
    "hdDate_att": 305,
    "hdDate_prod": 399,
    "hdDelete": 178,
    "hdDelete_att": 326,
    "hdDelete_prod": 413,
    "hdDirect_att": 307,
    "hdDiv1": 173,
    "hdDiv2": 174,
    "hdEdu_att": 320,
    "hdID": 159,
    "hdID_att": 304,
    "hdID_prod": 398,
    "hdIndirect_att": 308,
    "hdInputMH_prod": 409,
    "hdLeaveEarly_att": 317,
    "hdLine": 161,
    "hdLine_att": 306,
    "hdLine_prod": 400,
    "hdLostDiv_prod": 411,
    "hdLostMH_prod": 410,
    "hdLostReason_prod": 412,
    "hdMatManager_att": 324,
    "hdOverTime_att": 310,
    "hdPartName": 169,
    "hdPartNo": 168,
    "hdPicture": 171,
    "hdPlannedDown_att": 322,
    "hdPO": 163,
    "hdPO_prod": 402,
    "hdProcess": 167,
    "hdProcess_prod": 407,
    "hdProdQty_prod": 408,
    "hdProductNo": 164,
    "hdProductNo_prod": 403,
    "hdQty": 172,
    "hdRemark": 165,
    "hdRemark_att": 325,
    "hdRemark_prod": 405,
    "hdRest_att": 318,
    "hdReworkTime": 175,
    "hdShift": 166,
    "hdShift_prod": 406,
    "hdSiteManage_att": 323,
    "hdSN": 170,
    "hdSpec_prod": 404,
    "hdSupCell_att": 312,
    "hdSupported_att": 309,
    "hdSupQC_att": 313,
    "hdSupRnD_att": 314,
    "hdSupSys_att": 311,
    "hdTardy_att": 316,
    "hdType": 162,
    "hdType_prod": 401,
    "hdWorker": 176,
    "Host": 3,
    "Icon1_1": 280,
    "Icon10": 42,
    "Icon11": 40,
    "Icon12": 48,
    "Icon3": 50,
    "Icon4": 275,
    "Icon7": 276,
    "Icon7_1": 390,
    "Icon8": 389,
    "Icon9": 41,
    "iconAddRow": 538,
    "iconAlert": 44,
    "iconBiUpdate_def": 30,
    "iconBiUpdate_prod": 266,
    "iconExit_def": 131,
    "iconExit_wo": 278,
    "IconExitCommit_def": 228,
    "IconExitCommit_def_1": 452,
    "iconGrid": 128,
    "IconRefresh_prodhistory": 133,
    "Image3": 53,
    "imgPic": 223,
    "imgSetting": 24,
    "imgUser": 7,
    "Label10": 38,
    "Label2_1": 18,
    "Label3_2": 553,
    "Label4": 43,
    "Label5": 46,
    "Label5_1": 47,
    "Label5_2": 45,
    "LandingScreen": 565,
    "lb_caution": 568,
    "lbAbsentMH": 393,
    "lbAbsentMH_1": 383,
    "lbAvailMH": 395,
    "lbAvailMH_1": 385,
    "lbBuild_1": 26,
    "lbCommit_def": 229,
    "lbCommit_def_1": 453,
    "lbCustomer_wo": 287,
    "lbCustomer_wo2": 295,
    "lbCustomer2": 153,
    "lbCustomer3": 143,
    "lbDash_sn": 9,
    "lbDate2": 149,
    "lbDate3": 139,
    "lbDateSel_prod": 271,
    "lbFilterEndDate_def": 35,
    "lbFilterStartDate_def": 33,
    "lbFinance": 21,
    "lbGreeting": 6,
    "lbID": 182,
    "lbID_att": 330,
    "lbID_prod": 417,
    "lbLeftMH": 396,
    "lbLeftMH_1": 386,
    "lbLine_wo": 284,
    "lbLine_wo2": 293,
    "lbLine2": 135,
    "lbLineSel_prod": 269,
    "lbLostMH": 394,
    "lbLostMH_1": 384,
    "lbPO_wo": 286,
    "lbPO_wo2": 299,
    "lbPO2": 156,
    "lbPO3": 141,
    "lbProcess2": 157,
    "lbProcess3": 144,
    "lbProdHistory": 132,
    "lbProdHistory_1": 279,
    "lbProduction": 11,
    "lbProductNo_wo": 288,
    "lbProductNo_wo2": 296,
    "lbProductNo2": 152,
    "lbProductNo3": 142,
    "lbQty2": 154,
    "lbQty3": 145,
    "lbRefresh": 134,
    "lbRefresh_1": 281,
    "lbSpec_wo": 289,
    "lbSpec_wo2": 300,
    "lbTotalMH": 392,
    "lbTotalMH_1": 382,
    "lbtotalPOqty_wo": 290,
    "lbTotalPOqty_wo2": 297,
    "lbType_wo": 285,
    "lbType_wo2": 298,
    "lbType2": 155,
    "lbType3": 140,
    "lbWorker": 222,
    "Line_DataCard1": 58,
    "Line_DataCard2": 489,
    "Line_열1": 540,
    "Line_열2": 555,
    "Line_열3": 257,
    "logo": 25,
    "NextArrow4": 147,
    "NextArrow4_1": 301,
    "P.O_DataCard1": 509,
    "P.O_열1": 544,
    "PartName_DataCard1": 118,
    "PartNo_DataCard1": 113,
    "pbMiniDashScreen": 480,
    "pckDate_prod": 272,
    "pckEndDate": 36,
    "pckStartDate": 34,
    "Picture_DataCard1": 52,
    "PlanQty_열1": 564,
    "PO_DataCard1": 108,
    "PO_열1": 559,
    "Process_DataCard1": 103,
    "prod_check_2": 234,
    "prod_check_3": 459,
    "Prod_check_DataCard1_2": 231,
    "Prod_check_DataCard1_3": 456,
    "prodDefScreen": 28,
    "prodJobScreen": 264,
    "prodPlanScreen": 551,
    "ProductNo_DataCard1": 78,
    "ProductNo_DataCard2": 514,
    "ProductNo_열1": 545,
    "ProductNo_열2": 560,
    "ProductNo_열3": 258,
    "prodWorkOrderScreen": 484,
    "Project Name_DataCard1": 504,
    "Project Name_열1": 543,
    "ProjectName_DataCard1": 73,
    "ProjectName_열1": 558,
    "recImg": 207,
    "Rectangle4": 151,
    "Rectangle4_1": 294,
    "Remark_DataCard1": 88,
    "Remark_DataCard2": 524,
    "Remark_열1": 547,
    "Remark_열2": 562,
    "saveIcon": 129,
    "searchIcon": 127,
    "Separator4": 150,
    "Separator4_1": 302,
    "Shift_DataCard1": 98,
    "sideMenu": 5,
    "sideNavigation": 4,
    "sideNavigation_def": 29,
    "sideNavigation_Ld": 566,
    "sideNavigation_pb": 481,
    "sideNavigation_pb_1": 255,
    "sideNavigation_plan": 552,
    "sideNavigation_prod": 265,
    "sideNavigation_wo": 485,
    "Spec_DataCard1": 83,
    "Spec_DataCard2": 519,
    "Spec_열1": 546,
    "Spec_열2": 259,
    "StandardTime_열1": 261,
    "StartDate_열1": 262,
    "StarVisible10": 100,
    "StarVisible11": 105,
    "StarVisible12": 110,
    "StarVisible13": 115,
    "StarVisible14": 120,
    "StarVisible15": 55,
    "StarVisible16": 491,
    "StarVisible16_2": 232,
    "StarVisible16_3": 457,
    "StarVisible17": 496,
    "StarVisible17_2": 237,
    "StarVisible17_3": 462,
    "StarVisible18": 501,
    "StarVisible18_2": 242,
    "StarVisible18_3": 467,
    "StarVisible19": 506,
    "StarVisible19_2": 248,
    "StarVisible19_3": 473,
    "StarVisible2": 60,
    "StarVisible20": 511,
    "StarVisible21": 516,
    "StarVisible22": 521,
    "StarVisible23": 526,
    "StarVisible24": 531,
    "StarVisible3": 65,
    "StarVisible4": 70,
    "StarVisible5": 75,
    "StarVisible6": 80,
    "StarVisible7": 85,
    "StarVisible8": 90,
    "StarVisible9": 95,
    "Status_열1": 550,
    "STScreen": 254,
    "timerGreeting_Ld": 572,
    "Title_att": 267,
    "Title_def": 31,
    "Title_Ld": 567,
    "Title_pb": 482,
    "Title_prod": 380,
    "Title_wo": 486,
    "totalPOQty_DataCard1": 529,
    "totalPOQty_열1": 548,
    "totalProducedQty_열1": 549,
    "trashIcon_2": 375,
    "trashIcon_def": 219,
    "trashIcon_prod": 447,
    "txiAbsent_att": 353,
    "txiActionTaken": 218,
    "txiAssembly_att": 361,
    "txiCleaning_att": 365,
    "txiDate": 184,
    "txiDate_att": 332,
    "txiDate_prod": 419,
    "txiDirect_att": 336,
    "txiDiv2": 213,
    "txiEdu_att": 363,
    "txiIndirect_att": 339,
    "txiInputMH_prod": 439,
    "txiLeaveEarly_att": 357,
    "txiLine": 186,
    "txiLine_att": 334,
    "txiLine_prod": 421,
    "txiLostMH_prod": 441,
    "txiLostReason_prod": 445,
    "txiMatManage_att": 371,
    "txiOverTime_att": 343,
    "txiPartName": 202,
    "txiPartNo": 200,
    "txiPlannedDown_att": 367,
    "txiPO": 190,
    "txiPO_prod": 425,
    "txiProcess": 198,
    "txiProdQty_prod": 437,
    "txiProductNo": 192,
    "txiProductNo_prod": 427,
    "txiQty": 209,
    "txiRemark": 194,
    "txiRemark_att": 373,
    "txiRemark_prod": 431,
    "txiRest_att": 359,
    "txiReworkTime": 214,
    "txiShift": 196,
    "txiSiteManage_att": 369,
    "txiSN": 205,
    "txiSpec_prod": 429,
    "txiSupCell_att": 347,
    "txiSupported_att": 341,
    "txiSupQC_att": 349,
    "txiSupRnD_att": 351,
    "txiSupSys_att": 345,
    "txiTardy_att": 355,
    "txiType": 188,
    "txiType_prod": 423,
    "Type_DataCard1": 63,
    "Type_DataCard2": 494,
    "Type_열1": 541,
    "Type_열2": 556
  },
  "FunctionParamsInvariantScripts": {},
  "FunctionParamsInvariantScriptsOnInstances": {},
  "HeaderLastSavedDateTimeUTC": "11/07/2024 06:31:18",
  "IsLegacyComponentAllowGlobalScopeCase": false,
  "LocalConnectionIDReferences": {
    "f8d40288-c2d1-41bf-9761-1175340c181b": "\"/providers/microsoft.powerapps/apis/shared_sharepointonline/connections/a614d903fcdf4531bc467fef38a754a5\""
  },
  "LocalDatabaseReferencesAsEmpty": true,
  "LocalResourceFileNames": {
    "gear": "6ae72165-88fc-4136-83b7-640c858892e2.png",
    "left-arrow": "0e175895-8c9c-4296-b037-00c6e5f3a93f.gif",
    "refresh": "51e422ac-5814-44c1-a4d8-7a43d1950911.png",
    "round": "f916b7b1-93b9-4c4d-822a-ce5c9db19d04.png",
    "SE Energy Storage negative@2x (1)": "909759f3-fb98-4572-a887-b8c2a88454aa.png",
    "SE Energy Storage positive@2x (1)": "1ac3b3ce-f2c3-4571-ba17-6d944aa399ac.png",
    "update": "42d2a0cc-202a-4d50-a6d4-b95131f2db5e.png",
    "update_1": "13b8dae7-cdec-441c-a83a-2494110a9e99.png",
    "welcome": "6f03e9da-f39a-49fe-b9a2-dd2313952f85.gif"
  },
  "LocalResourceRootPaths": {
    "gear": "https://docserverpwaprodneu.blob.core.windows.net/4edf9fe2-23e7-4e90-b8b6-36410fa2bdf2-1/resource/Assets0Images06ae72165-88fc-4136-83b7-640c858892e2.png?skoid=58690ece-ec83-4ce2-9ce8-883d4d6a54ee&sktid=975f013f-7f24-47e8-a7d3-abc4752bf346&skt=2024-11-07T05%3A20%3A25Z&ske=2024-11-08T05%3A35%3A25Z&sks=b&skv=2023-01-03&sv=2023-01-03&spr=https&se=2024-11-08T05%3A35%3A25Z&sr=b&sp=r&sig=Xl9Bas6pmiRWPNuWi2GNSgH5F0Wq3PKNOiE79QIClrM%3D",
    "left-arrow": "https://docserverpwaprodneu.blob.core.windows.net/4edf9fe2-23e7-4e90-b8b6-36410fa2bdf2-1/resource/Assets0Images00e175895-8c9c-4296-b037-00c6e5f3a93f.gif?skoid=58690ece-ec83-4ce2-9ce8-883d4d6a54ee&sktid=975f013f-7f24-47e8-a7d3-abc4752bf346&skt=2024-11-07T05%3A20%3A25Z&ske=2024-11-08T05%3A35%3A25Z&sks=b&skv=2023-01-03&sv=2023-01-03&spr=https&se=2024-11-08T05%3A35%3A25Z&sr=b&sp=r&sig=9V%2BSNYOHzqRm32T33txlnbtax8WbLqOSVeZeBYrPQKE%3D",
    "refresh": "https://docserverpwaprodneu.blob.core.windows.net/4edf9fe2-23e7-4e90-b8b6-36410fa2bdf2-1/resource/Assets0Images051e422ac-5814-44c1-a4d8-7a43d1950911.png?skoid=58690ece-ec83-4ce2-9ce8-883d4d6a54ee&sktid=975f013f-7f24-47e8-a7d3-abc4752bf346&skt=2024-11-07T05%3A20%3A25Z&ske=2024-11-08T05%3A35%3A25Z&sks=b&skv=2023-01-03&sv=2023-01-03&spr=https&se=2024-11-08T05%3A35%3A25Z&sr=b&sp=r&sig=Ex6dzwtHcO33IckHvgxgQXeKzBey0ShJ25THvi6loNs%3D",
    "round": "https://docserverpwaprodneu.blob.core.windows.net/4edf9fe2-23e7-4e90-b8b6-36410fa2bdf2-1/resource/Assets0Images0f916b7b1-93b9-4c4d-822a-ce5c9db19d04.png?skoid=58690ece-ec83-4ce2-9ce8-883d4d6a54ee&sktid=975f013f-7f24-47e8-a7d3-abc4752bf346&skt=2024-11-07T05%3A20%3A25Z&ske=2024-11-08T05%3A35%3A25Z&sks=b&skv=2023-01-03&sv=2023-01-03&spr=https&se=2024-11-08T05%3A35%3A25Z&sr=b&sp=r&sig=Vj%2BXc3Y5pvF4Z2%2F74mbUbgTwpw5hxHvpqqO41bVdS3c%3D",
    "SE Energy Storage negative@2x (1)": "https://docserverpwaprodneu.blob.core.windows.net/4edf9fe2-23e7-4e90-b8b6-36410fa2bdf2-1/resource/Assets0Images0909759f3-fb98-4572-a887-b8c2a88454aa.png?skoid=58690ece-ec83-4ce2-9ce8-883d4d6a54ee&sktid=975f013f-7f24-47e8-a7d3-abc4752bf346&skt=2024-11-07T05%3A20%3A25Z&ske=2024-11-08T05%3A35%3A25Z&sks=b&skv=2023-01-03&sv=2023-01-03&spr=https&se=2024-11-08T05%3A35%3A25Z&sr=b&sp=r&sig=PyiGSt1K7iTxzAhHLuwKrOjbmRiJcrooHx49mb3YPUk%3D",
    "SE Energy Storage positive@2x (1)": "https://docserverpwaprodneu.blob.core.windows.net/4edf9fe2-23e7-4e90-b8b6-36410fa2bdf2-1/resource/Assets0Images01ac3b3ce-f2c3-4571-ba17-6d944aa399ac.png?skoid=58690ece-ec83-4ce2-9ce8-883d4d6a54ee&sktid=975f013f-7f24-47e8-a7d3-abc4752bf346&skt=2024-11-07T05%3A20%3A25Z&ske=2024-11-08T05%3A35%3A25Z&sks=b&skv=2023-01-03&sv=2023-01-03&spr=https&se=2024-11-08T05%3A35%3A25Z&sr=b&sp=r&sig=0ucvaQc8qG79SNRvhr0g53HzWi6RmyDXWABqyt9GL%2FE%3D",
    "update": "https://docserverpwaprodneu.blob.core.windows.net/4edf9fe2-23e7-4e90-b8b6-36410fa2bdf2-1/resource/Assets0Images042d2a0cc-202a-4d50-a6d4-b95131f2db5e.png?skoid=58690ece-ec83-4ce2-9ce8-883d4d6a54ee&sktid=975f013f-7f24-47e8-a7d3-abc4752bf346&skt=2024-11-07T05%3A20%3A25Z&ske=2024-11-08T05%3A35%3A25Z&sks=b&skv=2023-01-03&sv=2023-01-03&spr=https&se=2024-11-08T05%3A35%3A25Z&sr=b&sp=r&sig=aD8RWLIXN8uJcib9cTVXy3uzNaHNLgHHu968ARN6QOk%3D",
    "update_1": "https://docserverpwaprodneu.blob.core.windows.net/4edf9fe2-23e7-4e90-b8b6-36410fa2bdf2-1/resource/Assets0Images013b8dae7-cdec-441c-a83a-2494110a9e99.png?skoid=58690ece-ec83-4ce2-9ce8-883d4d6a54ee&sktid=975f013f-7f24-47e8-a7d3-abc4752bf346&skt=2024-11-07T05%3A20%3A25Z&ske=2024-11-08T05%3A35%3A25Z&sks=b&skv=2023-01-03&sv=2023-01-03&spr=https&se=2024-11-08T05%3A35%3A25Z&sr=b&sp=r&sig=TERdUBBOmKMytaBQvIPnUpMN4xz0UT%2FBbNGCV6q4uRw%3D",
    "welcome": "https://docserverpwaprodneu.blob.core.windows.net/4edf9fe2-23e7-4e90-b8b6-36410fa2bdf2-1/resource/Assets0Images06f03e9da-f39a-49fe-b9a2-dd2313952f85.gif?skoid=58690ece-ec83-4ce2-9ce8-883d4d6a54ee&sktid=975f013f-7f24-47e8-a7d3-abc4752bf346&skt=2024-11-07T05%3A20%3A25Z&ske=2024-11-08T05%3A35%3A25Z&sks=b&skv=2023-01-03&sv=2023-01-03&spr=https&se=2024-11-08T05%3A35%3A25Z&sr=b&sp=r&sig=pl9z%2Fh9fxqryxXpHGfB8YLVZsytSAUAtQhXi%2BoTOVvc%3D"
  },
  "OldLogoFileName": "wkhrvchy.jpg",
  "OrderComponentMetadata": {
    "94cc6ea9c3494c5d8a6a25904739c267": 0
  },
  "OrderComponentTemplate": {
    "94cc6ea9c3494c5d8a6a25904739c267": 0
  },
  "OrderDataSource": {
    "[HR_01]인사 정보": 7,
    "_db_processcode": 3,
    "_db_standardTime": 12,
    "_pdR_att": 6,
    "_pdR_commit_history": 9,
    "_pdR_plan": 11,
    "_pdR_prod": 8,
    "_pdR_prod_deleted": 13,
    "_pdR_unofficial_commit_history": 10,
    "_productionRecord": 1,
    "_workOrder": 4,
    "ComboBoxSample": 5,
    "CustomGallerySample": 0,
    "DropDownSample": 2
  },
  "OrderGroupControls": {
    "btnGroup_att": {
      "btnAdd_att": 0,
      "btnSave_att": 1,
      "Icon4": 2,
      "Icon7": 3
    },
    "btnGroup_def": {
      "btnGrid": 2,
      "btnSave": 1,
      "btnSearch": 0,
      "iconGrid": 4,
      "saveIcon": 5,
      "searchIcon": 3
    },
    "btnGroup_prod": {
      "btnSave_prod": 1,
      "btnSearch_prod": 0,
      "Icon7_1": 3,
      "Icon8": 2
    },
    "grpAddImg": {
      "addImgIcon": 0,
      "imgPic": 1
    },
    "grpSave": {
      "Button1": 1,
      "Icon3": 0
    }
  },
  "OrderPcfTemplate": {},
  "OrderTemplate": {},
  "OrderXMLTemplate": {
    "addMedia": 7,
    "button": 3,
    "checkbox": 10,
    "combobox": 13,
    "datepicker": 4,
    "dropdown": 9,
    "form": 6,
    "gallery": 11,
    "groupContainer": 0,
    "icon": 5,
    "image": 2,
    "label": 1,
    "powerbi": 16,
    "rectangle": 12,
    "text": 8,
    "timer": 15,
    "toggleSwitch": 14
  },
  "OverridablePropertiesEntry": {
    "2_lbMiniDash_sn": {},
    "addImgIcon": {},
    "AddPicture1": {},
    "App": {},
    "att_check_2": {},
    "att_check_3": {},
    "Att_check_DataCard1_2": {},
    "Att_check_DataCard1_3": {},
    "btnAdd_att": {},
    "btnAdd_wo": {},
    "btnCommit_def": {},
    "btnCommit_def_1": {},
    "btnCommitwithoutPatch": {},
    "btnCommitwithoutPatch_1": {},
    "btnDef": {},
    "btnGrid": {},
    "btnGroup_att": {},
    "btnGroup_def": {},
    "btnGroup_prod": {},
    "btnJob": {},
    "btnPlan": {},
    "btnPO": {},
    "btnSave": {},
    "btnSave_att": {},
    "btnSave_prod": {},
    "btnSearch": {},
    "btnSearch_prod": {},
    "btnST": {},
    "btnWP": {},
    "btnWP_1": {},
    "btnWP_2": {},
    "btnWP_3": {},
    "btnWP_4": {},
    "Button1": {},
    "Button2": {},
    "Button3": {},
    "ButtonTimer_prod": {},
    "cb_isClosed": {},
    "cbbWorker": {},
    "cbClosing": {},
    "cbInclWO": {},
    "Comment_DataCard1_2": {},
    "Comment_DataCard1_3": {},
    "commitForm_def": {},
    "commitForm_def_1": {},
    "contCommit_def": {},
    "contCommit_def_1": {},
    "contConfirm": {},
    "contDataTable_wo": {},
    "contEditForm": {},
    "contFilter_def": {},
    "contFilter_prod": {},
    "contForm": {},
    "contForm_att": {},
    "contForm_prod": {},
    "contHeader_att": {},
    "contHeader_def": {},
    "contHeader_mh": {},
    "contHeader_prod": {},
    "contHeader_wo": {},
    "contHeader3": {},
    "contNaviList": {},
    "contOutput_mh": {},
    "contWorkOrder": {},
    "contWorkOrder_prod": {},
    "Customer_DataCard1": {},
    "Customer_DataCard2": {},
    "Customer_열1": {},
    "Customer_열2": {},
    "DataCardKey10": {},
    "DataCardKey11": {},
    "DataCardKey12": {},
    "DataCardKey13": {},
    "DataCardKey14": {},
    "DataCardKey15": {},
    "DataCardKey16": {},
    "DataCardKey16_2": {},
    "DataCardKey16_3": {},
    "DataCardKey17": {},
    "DataCardKey17_2": {},
    "DataCardKey17_3": {},
    "DataCardKey18": {},
    "DataCardKey18_2": {},
    "DataCardKey18_3": {},
    "DataCardKey19": {},
    "DataCardKey19_2": {},
    "DataCardKey19_3": {},
    "DataCardKey2": {},
    "DataCardKey20": {},
    "DataCardKey21": {},
    "DataCardKey22": {},
    "DataCardKey23": {},
    "DataCardKey24": {},
    "DataCardKey3": {},
    "DataCardKey4": {},
    "DataCardKey5": {},
    "DataCardKey6": {},
    "DataCardKey7": {},
    "DataCardKey8": {},
    "DataCardKey9": {},
    "DataCardValue10": {},
    "DataCardValue11": {},
    "DataCardValue12": {},
    "DataCardValue13": {},
    "DataCardValue14": {},
    "DataCardValue15": {},
    "DataCardValue16": {},
    "DataCardValue17": {},
    "DataCardValue18": {},
    "DataCardValue18_2": {},
    "DataCardValue18_3": {},
    "DataCardValue19": {},
    "DataCardValue2": {},
    "DataCardValue20": {},
    "DataCardValue21": {},
    "DataCardValue22": {},
    "DataCardValue23": {},
    "DataCardValue3": {},
    "DataCardValue4": {},
    "DataCardValue5": {},
    "DataCardValue6": {},
    "DataCardValue7": {},
    "DataCardValue8": {},
    "DataCardValue9": {},
    "DataTable+wo": {},
    "DataTable2": {},
    "DataTable3": {},
    "Date_DataCard1": {},
    "Date_열1": {},
    "def_check_2": {},
    "def_check_3": {},
    "Def_check_DataCard1_2": {},
    "Def_check_DataCard1_3": {},
    "Description_열1": {},
    "Description_열2": {},
    "divider_prod": {},
    "Divider_sn": {},
    "divider1": {},
    "divider1_1": {},
    "divider1_10": {},
    "divider1_11": {},
    "divider1_12": {},
    "divider1_13": {},
    "divider1_15": {},
    "divider1_16": {},
    "divider1_17": {},
    "divider1_18": {},
    "divider1_19": {},
    "divider1_2": {},
    "divider1_20": {},
    "divider1_21": {},
    "divider1_22": {},
    "divider1_23": {},
    "divider1_24": {},
    "divider1_25": {},
    "divider1_26": {},
    "divider1_27": {},
    "divider1_28": {},
    "divider1_29": {},
    "divider1_3": {},
    "divider1_30": {},
    "divider1_31": {},
    "divider1_32": {},
    "divider1_33": {},
    "divider1_34": {},
    "divider1_35": {},
    "divider1_36": {},
    "divider1_37": {},
    "divider1_38": {},
    "divider1_39": {},
    "divider1_4": {},
    "divider1_40": {},
    "divider1_41": {},
    "divider1_42": {},
    "divider1_43": {},
    "divider1_44": {},
    "divider1_45": {},
    "divider1_46": {},
    "divider1_47": {},
    "divider1_48": {},
    "divider1_49": {},
    "divider1_5": {},
    "divider1_50": {},
    "divider1_51": {},
    "divider1_52": {},
    "divider1_53": {},
    "divider1_54": {},
    "divider1_55": {},
    "divider1_56": {},
    "divider1_57": {},
    "divider1_58": {},
    "divider1_59": {},
    "divider1_6": {},
    "divider1_60": {},
    "divider1_61": {},
    "divider1_62": {},
    "divider1_63": {},
    "divider1_64": {},
    "divider1_65": {},
    "divider1_7": {},
    "divider1_8": {},
    "divider1_9": {},
    "drpDiv1": {},
    "drpLineSel": {},
    "drpLineSel_prod": {},
    "drpLostDiv_prod": {},
    "drpProcess_prod": {},
    "drpShift_prod": {},
    "EditForm": {},
    "embededPowerBI": {},
    "EndDate_열1": {},
    "ErrorMessage10": {},
    "ErrorMessage11": {},
    "ErrorMessage12": {},
    "ErrorMessage13": {},
    "ErrorMessage14": {},
    "ErrorMessage15": {},
    "ErrorMessage16": {},
    "ErrorMessage16_2": {},
    "ErrorMessage16_3": {},
    "ErrorMessage17": {},
    "ErrorMessage17_2": {},
    "ErrorMessage17_3": {},
    "ErrorMessage18": {},
    "ErrorMessage18_2": {},
    "ErrorMessage18_3": {},
    "ErrorMessage19": {},
    "ErrorMessage19_2": {},
    "ErrorMessage19_3": {},
    "ErrorMessage2": {},
    "ErrorMessage20": {},
    "ErrorMessage21": {},
    "ErrorMessage22": {},
    "ErrorMessage23": {},
    "ErrorMessage24": {},
    "ErrorMessage3": {},
    "ErrorMessage4": {},
    "ErrorMessage5": {},
    "ErrorMessage6": {},
    "ErrorMessage7": {},
    "ErrorMessage8": {},
    "ErrorMessage9": {},
    "Form1": {},
    "galleryTemplate1": {},
    "galleryTemplate1_1": {},
    "galleryTemplate1_2": {},
    "galleryTemplate2": {},
    "galleryTemplate2_1": {},
    "galProdHistory": {},
    "galWorkOrder": {},
    "gifGreetingFox": {},
    "gifLeftArrow": {},
    "Greeting_Ld": {},
    "gridForm_att": {},
    "gridForm_def": {},
    "gridForm_prod": {},
    "grpAddImg": {},
    "grpSave": {},
    "hdAbsent_att": {},
    "hdActionTaken": {},
    "hdAssembly_att": {},
    "hdCleaning_att": {},
    "hdDate": {},
    "hdDate_att": {},
    "hdDate_prod": {},
    "hdDelete": {},
    "hdDelete_att": {},
    "hdDelete_prod": {},
    "hdDirect_att": {},
    "hdDiv1": {},
    "hdDiv2": {},
    "hdEdu_att": {},
    "hdID": {},
    "hdID_att": {},
    "hdID_prod": {},
    "hdIndirect_att": {},
    "hdInputMH_prod": {},
    "hdLeaveEarly_att": {},
    "hdLine": {},
    "hdLine_att": {},
    "hdLine_prod": {},
    "hdLostDiv_prod": {},
    "hdLostMH_prod": {},
    "hdLostReason_prod": {},
    "hdMatManager_att": {},
    "hdOverTime_att": {},
    "hdPartName": {},
    "hdPartNo": {},
    "hdPicture": {},
    "hdPlannedDown_att": {},
    "hdPO": {},
    "hdPO_prod": {},
    "hdProcess": {},
    "hdProcess_prod": {},
    "hdProdQty_prod": {},
    "hdProductNo": {},
    "hdProductNo_prod": {},
    "hdQty": {},
    "hdRemark": {},
    "hdRemark_att": {},
    "hdRemark_prod": {},
    "hdRest_att": {},
    "hdReworkTime": {},
    "hdShift": {},
    "hdShift_prod": {},
    "hdSiteManage_att": {},
    "hdSN": {},
    "hdSpec_prod": {},
    "hdSupCell_att": {},
    "hdSupported_att": {},
    "hdSupQC_att": {},
    "hdSupRnD_att": {},
    "hdSupSys_att": {},
    "hdTardy_att": {},
    "hdType": {},
    "hdType_prod": {},
    "hdWorker": {},
    "Host": {},
    "Icon1_1": {},
    "Icon10": {},
    "Icon11": {},
    "Icon12": {},
    "Icon3": {},
    "Icon4": {},
    "Icon7": {},
    "Icon7_1": {},
    "Icon8": {},
    "Icon9": {},
    "iconAddRow": {},
    "iconAlert": {},
    "iconBiUpdate_def": {},
    "iconBiUpdate_prod": {},
    "iconExit_def": {},
    "iconExit_wo": {},
    "IconExitCommit_def": {},
    "IconExitCommit_def_1": {},
    "iconGrid": {},
    "IconRefresh_prodhistory": {},
    "Image3": {},
    "imgPic": {},
    "imgSetting": {},
    "imgUser": {},
    "Label10": {},
    "Label2_1": {},
    "Label3_2": {},
    "Label4": {},
    "Label5": {},
    "Label5_1": {},
    "Label5_2": {},
    "LandingScreen": {},
    "lb_caution": {},
    "lbAbsentMH": {},
    "lbAbsentMH_1": {},
    "lbAvailMH": {},
    "lbAvailMH_1": {},
    "lbBuild_1": {},
    "lbCommit_def": {},
    "lbCommit_def_1": {},
    "lbCustomer_wo": {},
    "lbCustomer_wo2": {},
    "lbCustomer2": {},
    "lbCustomer3": {},
    "lbDash_sn": {},
    "lbDate2": {},
    "lbDate3": {},
    "lbDateSel_prod": {},
    "lbFilterEndDate_def": {},
    "lbFilterStartDate_def": {},
    "lbFinance": {},
    "lbGreeting": {},
    "lbID": {},
    "lbID_att": {},
    "lbID_prod": {},
    "lbLeftMH": {},
    "lbLeftMH_1": {},
    "lbLine_wo": {},
    "lbLine_wo2": {},
    "lbLine2": {},
    "lbLineSel_prod": {},
    "lbLostMH": {},
    "lbLostMH_1": {},
    "lbPO_wo": {},
    "lbPO_wo2": {},
    "lbPO2": {},
    "lbPO3": {},
    "lbProcess2": {},
    "lbProcess3": {},
    "lbProdHistory": {},
    "lbProdHistory_1": {},
    "lbProduction": {},
    "lbProductNo_wo": {},
    "lbProductNo_wo2": {},
    "lbProductNo2": {},
    "lbProductNo3": {},
    "lbQty2": {},
    "lbQty3": {},
    "lbRefresh": {},
    "lbRefresh_1": {},
    "lbSpec_wo": {},
    "lbSpec_wo2": {},
    "lbTotalMH": {},
    "lbTotalMH_1": {},
    "lbtotalPOqty_wo": {},
    "lbTotalPOqty_wo2": {},
    "lbType_wo": {},
    "lbType_wo2": {},
    "lbType2": {},
    "lbType3": {},
    "lbWorker": {},
    "Line_DataCard1": {},
    "Line_DataCard2": {},
    "Line_열1": {},
    "Line_열2": {},
    "Line_열3": {},
    "logo": {},
    "NextArrow4": {},
    "NextArrow4_1": {},
    "P.O_DataCard1": {},
    "P.O_열1": {},
    "PartName_DataCard1": {},
    "PartNo_DataCard1": {},
    "pbMiniDashScreen": {},
    "pckDate_prod": {},
    "pckEndDate": {},
    "pckStartDate": {},
    "Picture_DataCard1": {},
    "PlanQty_열1": {},
    "PO_DataCard1": {},
    "PO_열1": {},
    "Process_DataCard1": {},
    "prod_check_2": {},
    "prod_check_3": {},
    "Prod_check_DataCard1_2": {},
    "Prod_check_DataCard1_3": {},
    "prodDefScreen": {},
    "prodJobScreen": {},
    "prodPlanScreen": {},
    "ProductNo_DataCard1": {},
    "ProductNo_DataCard2": {},
    "ProductNo_열1": {},
    "ProductNo_열2": {},
    "ProductNo_열3": {},
    "prodWorkOrderScreen": {},
    "Project Name_DataCard1": {},
    "Project Name_열1": {},
    "ProjectName_DataCard1": {},
    "ProjectName_열1": {},
    "recImg": {},
    "Rectangle4": {},
    "Rectangle4_1": {},
    "Remark_DataCard1": {},
    "Remark_DataCard2": {},
    "Remark_열1": {},
    "Remark_열2": {},
    "saveIcon": {},
    "searchIcon": {},
    "Separator4": {},
    "Separator4_1": {},
    "Shift_DataCard1": {},
    "sideMenu": {},
    "sideNavigation": {},
    "sideNavigation_def": {},
    "sideNavigation_Ld": {},
    "sideNavigation_pb": {},
    "sideNavigation_pb_1": {},
    "sideNavigation_plan": {},
    "sideNavigation_prod": {},
    "sideNavigation_wo": {},
    "Spec_DataCard1": {},
    "Spec_DataCard2": {},
    "Spec_열1": {},
    "Spec_열2": {},
    "StandardTime_열1": {},
    "StartDate_열1": {},
    "StarVisible10": {},
    "StarVisible11": {},
    "StarVisible12": {},
    "StarVisible13": {},
    "StarVisible14": {},
    "StarVisible15": {},
    "StarVisible16": {},
    "StarVisible16_2": {},
    "StarVisible16_3": {},
    "StarVisible17": {},
    "StarVisible17_2": {},
    "StarVisible17_3": {},
    "StarVisible18": {},
    "StarVisible18_2": {},
    "StarVisible18_3": {},
    "StarVisible19": {},
    "StarVisible19_2": {},
    "StarVisible19_3": {},
    "StarVisible2": {},
    "StarVisible20": {},
    "StarVisible21": {},
    "StarVisible22": {},
    "StarVisible23": {},
    "StarVisible24": {},
    "StarVisible3": {},
    "StarVisible4": {},
    "StarVisible5": {},
    "StarVisible6": {},
    "StarVisible7": {},
    "StarVisible8": {},
    "StarVisible9": {},
    "Status_열1": {},
    "STScreen": {},
    "timerGreeting_Ld": {},
    "Title_att": {},
    "Title_def": {},
    "Title_Ld": {},
    "Title_pb": {},
    "Title_prod": {},
    "Title_wo": {},
    "totalPOQty_DataCard1": {},
    "totalPOQty_열1": {},
    "totalProducedQty_열1": {},
    "trashIcon_2": {},
    "trashIcon_def": {},
    "trashIcon_prod": {},
    "txiAbsent_att": {},
    "txiActionTaken": {},
    "txiAssembly_att": {},
    "txiCleaning_att": {},
    "txiDate": {},
    "txiDate_att": {},
    "txiDate_prod": {},
    "txiDirect_att": {},
    "txiDiv2": {},
    "txiEdu_att": {},
    "txiIndirect_att": {},
    "txiInputMH_prod": {},
    "txiLeaveEarly_att": {},
    "txiLine": {},
    "txiLine_att": {},
    "txiLine_prod": {},
    "txiLostMH_prod": {},
    "txiLostReason_prod": {},
    "txiMatManage_att": {},
    "txiOverTime_att": {},
    "txiPartName": {},
    "txiPartNo": {},
    "txiPlannedDown_att": {},
    "txiPO": {},
    "txiPO_prod": {},
    "txiProcess": {},
    "txiProdQty_prod": {},
    "txiProductNo": {},
    "txiProductNo_prod": {},
    "txiQty": {},
    "txiRemark": {},
    "txiRemark_att": {},
    "txiRemark_prod": {},
    "txiRest_att": {},
    "txiReworkTime": {},
    "txiShift": {},
    "txiSiteManage_att": {},
    "txiSN": {},
    "txiSpec_prod": {},
    "txiSupCell_att": {},
    "txiSupported_att": {},
    "txiSupQC_att": {},
    "txiSupRnD_att": {},
    "txiSupSys_att": {},
    "txiTardy_att": {},
    "txiType": {},
    "txiType_prod": {},
    "Type_DataCard1": {},
    "Type_DataCard2": {},
    "Type_열1": {},
    "Type_열2": {}
  },
  "PCFDynamicSchemaForIRRetrievalEntry": {},
  "PCFTemplateEntry": {},
  "PublishOrderIndices": {
    "2_lbMiniDash_sn": 543,
    "addImgIcon": 421,
    "AddPicture1": 251,
    "App": 0,
    "att_check_2": 441,
    "att_check_3": 216,
    "Att_check_DataCard1_2": 438,
    "Att_check_DataCard1_3": 213,
    "btnAdd_att": 20,
    "btnAdd_wo": 502,
    "btnCommit_def": 449,
    "btnCommit_def_1": 224,
    "btnCommitwithoutPatch": 448,
    "btnCommitwithoutPatch_1": 223,
    "btnDef": 546,
    "btnGrid": 323,
    "btnGroup_att": 18,
    "btnGroup_def": 320,
    "btnGroup_prod": 19,
    "btnJob": 545,
    "btnPlan": 548,
    "btnPO": 547,
    "btnSave": 322,
    "btnSave_att": 21,
    "btnSave_prod": 135,
    "btnSearch": 321,
    "btnSearch_prod": 134,
    "btnST": 549,
    "btnWP": 550,
    "btnWP_1": 553,
    "btnWP_2": 552,
    "btnWP_3": 555,
    "btnWP_4": 556,
    "Button1": 245,
    "Button2": 499,
    "Button3": 500,
    "ButtonTimer_prod": 201,
    "cb_isClosed": 29,
    "cbbWorker": 413,
    "cbClosing": 501,
    "cbInclWO": 334,
    "Comment_DataCard1_2": 443,
    "Comment_DataCard1_3": 218,
    "commitForm_def": 427,
    "commitForm_def_1": 202,
    "contCommit_def": 424,
    "contCommit_def_1": 198,
    "contConfirm": 235,
    "contDataTable_wo": 452,
    "contEditForm": 233,
    "contFilter_def": 228,
    "contFilter_prod": 13,
    "contForm": 376,
    "contForm_att": 74,
    "contForm_prod": 161,
    "contHeader_att": 50,
    "contHeader_def": 355,
    "contHeader_mh": 128,
    "contHeader_prod": 144,
    "contHeader_wo": 30,
    "contHeader3": 335,
    "contNaviList": 541,
    "contOutput_mh": 138,
    "contWorkOrder": 327,
    "contWorkOrder_prod": 24,
    "Customer_DataCard1": 265,
    "Customer_DataCard2": 464,
    "Customer_열1": 507,
    "Customer_열2": 521,
    "DataCardKey10": 298,
    "DataCardKey11": 303,
    "DataCardKey12": 308,
    "DataCardKey13": 313,
    "DataCardKey14": 318,
    "DataCardKey15": 253,
    "DataCardKey16": 457,
    "DataCardKey16_2": 430,
    "DataCardKey16_3": 205,
    "DataCardKey17": 462,
    "DataCardKey17_2": 435,
    "DataCardKey17_3": 210,
    "DataCardKey18": 467,
    "DataCardKey18_2": 440,
    "DataCardKey18_3": 215,
    "DataCardKey19": 472,
    "DataCardKey19_2": 446,
    "DataCardKey19_3": 221,
    "DataCardKey2": 258,
    "DataCardKey20": 477,
    "DataCardKey21": 482,
    "DataCardKey22": 487,
    "DataCardKey23": 492,
    "DataCardKey24": 497,
    "DataCardKey3": 263,
    "DataCardKey4": 268,
    "DataCardKey5": 273,
    "DataCardKey6": 278,
    "DataCardKey7": 283,
    "DataCardKey8": 288,
    "DataCardKey9": 293,
    "DataCardValue10": 296,
    "DataCardValue11": 301,
    "DataCardValue12": 306,
    "DataCardValue13": 311,
    "DataCardValue14": 316,
    "DataCardValue15": 455,
    "DataCardValue16": 460,
    "DataCardValue17": 465,
    "DataCardValue18": 470,
    "DataCardValue18_2": 444,
    "DataCardValue18_3": 219,
    "DataCardValue19": 475,
    "DataCardValue2": 256,
    "DataCardValue20": 480,
    "DataCardValue21": 485,
    "DataCardValue22": 490,
    "DataCardValue23": 495,
    "DataCardValue3": 261,
    "DataCardValue4": 266,
    "DataCardValue5": 271,
    "DataCardValue6": 276,
    "DataCardValue7": 281,
    "DataCardValue8": 286,
    "DataCardValue9": 291,
    "DataTable+wo": 504,
    "DataTable2": 518,
    "DataTable3": 530,
    "Date_DataCard1": 290,
    "Date_열1": 527,
    "def_check_2": 436,
    "def_check_3": 211,
    "Def_check_DataCard1_2": 433,
    "Def_check_DataCard1_3": 208,
    "Description_열1": 525,
    "Description_열2": 534,
    "divider_prod": 126,
    "Divider_sn": 560,
    "divider1": 380,
    "divider1_1": 382,
    "divider1_10": 400,
    "divider1_11": 405,
    "divider1_12": 407,
    "divider1_13": 409,
    "divider1_15": 412,
    "divider1_16": 414,
    "divider1_17": 401,
    "divider1_18": 418,
    "divider1_19": 423,
    "divider1_2": 384,
    "divider1_20": 403,
    "divider1_21": 165,
    "divider1_22": 167,
    "divider1_23": 169,
    "divider1_24": 171,
    "divider1_25": 173,
    "divider1_26": 175,
    "divider1_27": 177,
    "divider1_28": 179,
    "divider1_29": 181,
    "divider1_3": 386,
    "divider1_30": 183,
    "divider1_31": 185,
    "divider1_32": 187,
    "divider1_33": 189,
    "divider1_34": 191,
    "divider1_35": 193,
    "divider1_36": 195,
    "divider1_37": 78,
    "divider1_38": 93,
    "divider1_39": 80,
    "divider1_4": 388,
    "divider1_40": 197,
    "divider1_41": 82,
    "divider1_42": 84,
    "divider1_43": 196,
    "divider1_44": 87,
    "divider1_45": 85,
    "divider1_46": 89,
    "divider1_47": 91,
    "divider1_48": 95,
    "divider1_49": 97,
    "divider1_5": 390,
    "divider1_50": 99,
    "divider1_51": 101,
    "divider1_52": 103,
    "divider1_53": 123,
    "divider1_54": 125,
    "divider1_55": 105,
    "divider1_56": 107,
    "divider1_57": 109,
    "divider1_58": 111,
    "divider1_59": 113,
    "divider1_6": 392,
    "divider1_60": 115,
    "divider1_61": 117,
    "divider1_62": 119,
    "divider1_63": 121,
    "divider1_64": 124,
    "divider1_65": 417,
    "divider1_7": 394,
    "divider1_8": 396,
    "divider1_9": 398,
    "drpDiv1": 408,
    "drpLineSel": 333,
    "drpLineSel_prod": 15,
    "drpLostDiv_prod": 190,
    "drpProcess_prod": 182,
    "drpShift_prod": 180,
    "EditForm": 248,
    "embededPowerBI": 9,
    "EndDate_열1": 537,
    "ErrorMessage10": 299,
    "ErrorMessage11": 304,
    "ErrorMessage12": 309,
    "ErrorMessage13": 314,
    "ErrorMessage14": 319,
    "ErrorMessage15": 254,
    "ErrorMessage16": 458,
    "ErrorMessage16_2": 432,
    "ErrorMessage16_3": 207,
    "ErrorMessage17": 463,
    "ErrorMessage17_2": 437,
    "ErrorMessage17_3": 212,
    "ErrorMessage18": 468,
    "ErrorMessage18_2": 442,
    "ErrorMessage18_3": 217,
    "ErrorMessage19": 473,
    "ErrorMessage19_2": 447,
    "ErrorMessage19_3": 222,
    "ErrorMessage2": 259,
    "ErrorMessage20": 478,
    "ErrorMessage21": 483,
    "ErrorMessage22": 488,
    "ErrorMessage23": 493,
    "ErrorMessage24": 498,
    "ErrorMessage3": 264,
    "ErrorMessage4": 269,
    "ErrorMessage5": 274,
    "ErrorMessage6": 279,
    "ErrorMessage7": 284,
    "ErrorMessage8": 289,
    "ErrorMessage9": 294,
    "Form1": 453,
    "galleryTemplate1": 378,
    "galleryTemplate1_1": 163,
    "galleryTemplate1_2": 76,
    "galleryTemplate2": 345,
    "galleryTemplate2_1": 39,
    "galProdHistory": 343,
    "galWorkOrder": 38,
    "gifGreetingFox": 5,
    "gifLeftArrow": 3,
    "Greeting_Ld": 4,
    "gridForm_att": 75,
    "gridForm_def": 377,
    "gridForm_prod": 162,
    "grpAddImg": 422,
    "grpSave": 246,
    "hdAbsent_att": 62,
    "hdActionTaken": 374,
    "hdAssembly_att": 66,
    "hdCleaning_att": 68,
    "hdDate": 357,
    "hdDate_att": 52,
    "hdDate_prod": 146,
    "hdDelete": 375,
    "hdDelete_att": 73,
    "hdDelete_prod": 160,
    "hdDirect_att": 54,
    "hdDiv1": 370,
    "hdDiv2": 371,
    "hdEdu_att": 67,
    "hdID": 356,
    "hdID_att": 51,
    "hdID_prod": 145,
    "hdIndirect_att": 55,
    "hdInputMH_prod": 156,
    "hdLeaveEarly_att": 64,
    "hdLine": 358,
    "hdLine_att": 53,
    "hdLine_prod": 147,
    "hdLostDiv_prod": 158,
    "hdLostMH_prod": 157,
    "hdLostReason_prod": 159,
    "hdMatManager_att": 71,
    "hdOverTime_att": 57,
    "hdPartName": 366,
    "hdPartNo": 365,
    "hdPicture": 368,
    "hdPlannedDown_att": 69,
    "hdPO": 360,
    "hdPO_prod": 149,
    "hdProcess": 364,
    "hdProcess_prod": 154,
    "hdProdQty_prod": 155,
    "hdProductNo": 361,
    "hdProductNo_prod": 150,
    "hdQty": 369,
    "hdRemark": 362,
    "hdRemark_att": 72,
    "hdRemark_prod": 152,
    "hdRest_att": 65,
    "hdReworkTime": 372,
    "hdShift": 363,
    "hdShift_prod": 153,
    "hdSiteManage_att": 70,
    "hdSN": 367,
    "hdSpec_prod": 151,
    "hdSupCell_att": 59,
    "hdSupported_att": 56,
    "hdSupQC_att": 60,
    "hdSupRnD_att": 61,
    "hdSupSys_att": 58,
    "hdTardy_att": 63,
    "hdType": 359,
    "hdType_prod": 148,
    "hdWorker": 373,
    "Host": 0,
    "Icon1_1": 27,
    "Icon10": 238,
    "Icon11": 236,
    "Icon12": 244,
    "Icon3": 247,
    "Icon4": 22,
    "Icon7": 23,
    "Icon7_1": 137,
    "Icon8": 136,
    "Icon9": 237,
    "iconAddRow": 503,
    "iconAlert": 240,
    "iconBiUpdate_def": 226,
    "iconBiUpdate_prod": 11,
    "iconExit_def": 328,
    "iconExit_wo": 25,
    "IconExitCommit_def": 425,
    "IconExitCommit_def_1": 199,
    "iconGrid": 325,
    "IconRefresh_prodhistory": 330,
    "Image3": 250,
    "imgPic": 420,
    "imgSetting": 557,
    "imgUser": 540,
    "Label10": 234,
    "Label2_1": 551,
    "Label3_2": 517,
    "Label4": 239,
    "Label5": 242,
    "Label5_1": 243,
    "Label5_2": 241,
    "LandingScreen": 0,
    "lb_caution": 2,
    "lbAbsentMH": 140,
    "lbAbsentMH_1": 130,
    "lbAvailMH": 142,
    "lbAvailMH_1": 132,
    "lbBuild_1": 559,
    "lbCommit_def": 426,
    "lbCommit_def_1": 200,
    "lbCustomer_wo": 34,
    "lbCustomer_wo2": 42,
    "lbCustomer2": 350,
    "lbCustomer3": 340,
    "lbDash_sn": 542,
    "lbDate2": 346,
    "lbDate3": 336,
    "lbDateSel_prod": 16,
    "lbFilterEndDate_def": 231,
    "lbFilterStartDate_def": 229,
    "lbFinance": 554,
    "lbGreeting": 539,
    "lbID": 379,
    "lbID_att": 77,
    "lbID_prod": 164,
    "lbLeftMH": 143,
    "lbLeftMH_1": 133,
    "lbLine_wo": 31,
    "lbLine_wo2": 40,
    "lbLine2": 332,
    "lbLineSel_prod": 14,
    "lbLostMH": 141,
    "lbLostMH_1": 131,
    "lbPO_wo": 33,
    "lbPO_wo2": 46,
    "lbPO2": 353,
    "lbPO3": 338,
    "lbProcess2": 354,
    "lbProcess3": 341,
    "lbProdHistory": 329,
    "lbProdHistory_1": 26,
    "lbProduction": 544,
    "lbProductNo_wo": 35,
    "lbProductNo_wo2": 43,
    "lbProductNo2": 349,
    "lbProductNo3": 339,
    "lbQty2": 351,
    "lbQty3": 342,
    "lbRefresh": 331,
    "lbRefresh_1": 28,
    "lbSpec_wo": 36,
    "lbSpec_wo2": 47,
    "lbTotalMH": 139,
    "lbTotalMH_1": 129,
    "lbtotalPOqty_wo": 37,
    "lbTotalPOqty_wo2": 44,
    "lbType_wo": 32,
    "lbType_wo2": 45,
    "lbType2": 352,
    "lbType3": 337,
    "lbWorker": 419,
    "Line_DataCard1": 255,
    "Line_DataCard2": 454,
    "Line_열1": 505,
    "Line_열2": 519,
    "Line_열3": 531,
    "logo": 558,
    "NextArrow4": 344,
    "NextArrow4_1": 48,
    "P.O_DataCard1": 474,
    "P.O_열1": 509,
    "PartName_DataCard1": 315,
    "PartNo_DataCard1": 310,
    "pbMiniDashScreen": 0,
    "pckDate_prod": 17,
    "pckEndDate": 232,
    "pckStartDate": 230,
    "Picture_DataCard1": 249,
    "PlanQty_열1": 528,
    "PO_DataCard1": 305,
    "PO_열1": 523,
    "Process_DataCard1": 300,
    "prod_check_2": 431,
    "prod_check_3": 206,
    "Prod_check_DataCard1_2": 428,
    "Prod_check_DataCard1_3": 203,
    "prodDefScreen": 0,
    "prodJobScreen": 0,
    "prodPlanScreen": 0,
    "ProductNo_DataCard1": 275,
    "ProductNo_DataCard2": 479,
    "ProductNo_열1": 510,
    "ProductNo_열2": 524,
    "ProductNo_열3": 532,
    "prodWorkOrderScreen": 0,
    "Project Name_DataCard1": 469,
    "Project Name_열1": 508,
    "ProjectName_DataCard1": 270,
    "ProjectName_열1": 522,
    "recImg": 404,
    "Rectangle4": 348,
    "Rectangle4_1": 41,
    "Remark_DataCard1": 285,
    "Remark_DataCard2": 489,
    "Remark_열1": 512,
    "Remark_열2": 526,
    "saveIcon": 326,
    "searchIcon": 324,
    "Separator4": 347,
    "Separator4_1": 49,
    "Shift_DataCard1": 295,
    "sideMenu": 538,
    "sideNavigation": 0,
    "sideNavigation_def": 225,
    "sideNavigation_Ld": 0,
    "sideNavigation_pb": 7,
    "sideNavigation_pb_1": 529,
    "sideNavigation_plan": 516,
    "sideNavigation_prod": 10,
    "sideNavigation_wo": 450,
    "Spec_DataCard1": 280,
    "Spec_DataCard2": 484,
    "Spec_열1": 511,
    "Spec_열2": 533,
    "StandardTime_열1": 535,
    "StartDate_열1": 536,
    "StarVisible10": 297,
    "StarVisible11": 302,
    "StarVisible12": 307,
    "StarVisible13": 312,
    "StarVisible14": 317,
    "StarVisible15": 252,
    "StarVisible16": 456,
    "StarVisible16_2": 429,
    "StarVisible16_3": 204,
    "StarVisible17": 461,
    "StarVisible17_2": 434,
    "StarVisible17_3": 209,
    "StarVisible18": 466,
    "StarVisible18_2": 439,
    "StarVisible18_3": 214,
    "StarVisible19": 471,
    "StarVisible19_2": 445,
    "StarVisible19_3": 220,
    "StarVisible2": 257,
    "StarVisible20": 476,
    "StarVisible21": 481,
    "StarVisible22": 486,
    "StarVisible23": 491,
    "StarVisible24": 496,
    "StarVisible3": 262,
    "StarVisible4": 267,
    "StarVisible5": 272,
    "StarVisible6": 277,
    "StarVisible7": 282,
    "StarVisible8": 287,
    "StarVisible9": 292,
    "Status_열1": 515,
    "STScreen": 0,
    "timerGreeting_Ld": 6,
    "Title_att": 12,
    "Title_def": 227,
    "Title_Ld": 1,
    "Title_pb": 8,
    "Title_prod": 127,
    "Title_wo": 451,
    "totalPOQty_DataCard1": 494,
    "totalPOQty_열1": 513,
    "totalProducedQty_열1": 514,
    "trashIcon_2": 122,
    "trashIcon_def": 416,
    "trashIcon_prod": 194,
    "txiAbsent_att": 100,
    "txiActionTaken": 415,
    "txiAssembly_att": 108,
    "txiCleaning_att": 112,
    "txiDate": 381,
    "txiDate_att": 79,
    "txiDate_prod": 166,
    "txiDirect_att": 83,
    "txiDiv2": 410,
    "txiEdu_att": 110,
    "txiIndirect_att": 86,
    "txiInputMH_prod": 186,
    "txiLeaveEarly_att": 104,
    "txiLine": 383,
    "txiLine_att": 81,
    "txiLine_prod": 168,
    "txiLostMH_prod": 188,
    "txiLostReason_prod": 192,
    "txiMatManage_att": 118,
    "txiOverTime_att": 90,
    "txiPartName": 399,
    "txiPartNo": 397,
    "txiPlannedDown_att": 114,
    "txiPO": 387,
    "txiPO_prod": 172,
    "txiProcess": 395,
    "txiProdQty_prod": 184,
    "txiProductNo": 389,
    "txiProductNo_prod": 174,
    "txiQty": 406,
    "txiRemark": 391,
    "txiRemark_att": 120,
    "txiRemark_prod": 178,
    "txiRest_att": 106,
    "txiReworkTime": 411,
    "txiShift": 393,
    "txiSiteManage_att": 116,
    "txiSN": 402,
    "txiSpec_prod": 176,
    "txiSupCell_att": 94,
    "txiSupported_att": 88,
    "txiSupQC_att": 96,
    "txiSupRnD_att": 98,
    "txiSupSys_att": 92,
    "txiTardy_att": 102,
    "txiType": 385,
    "txiType_prod": 170,
    "Type_DataCard1": 260,
    "Type_DataCard2": 459,
    "Type_열1": 506,
    "Type_열2": 520
  },
  "ResourcesJsonIndices": {
    "Image-gear": 5,
    "Image-left-arrow": 9,
    "Image-refresh": 4,
    "Image-round": 6,
    "Image-SampleImage": 0,
    "Image-SE Energy Storage negative@2x (1)": 3,
    "Image-SE Energy Storage positive@2x (1)": 1,
    "Image-update": 2,
    "Image-update_1": 7,
    "Image-welcome": 8
  },
  "RuleScreenIdWithoutScreen": {},
  "TemplateVersions": {},
  "VolatileProperties": {
    "AnalysisLoadTime": 3.7450477,
    "ControlCount": {
      "94cc6ea9c3494c5d8a6a25904739c267": 8,
      "addMedia": 1,
      "button": 26,
      "checkbox": 3,
      "combobox": 1,
      "dataTable": 3,
      "dataTableColumn": 28,
      "datepicker": 4,
      "dropdown": 6,
      "form": 4,
      "gallery": 5,
      "galleryTemplate": 5,
      "group": 5,
      "groupContainer": 88,
      "icon": 26,
      "image": 9,
      "label": 225,
      "powerbi": 1,
      "rectangle": 5,
      "screen": 7,
      "text": 70,
      "timer": 2,
      "toggleSwitch": 6,
      "typedDataCard": 31
    },
    "DeserializationLoadTime": 4.417219
  },
  "WasLocalDatabaseReferencesEmpty": true
}